tw_finreport_scraper/__init__.py
tw_finreport_scraper/__main__.py
tw_finreport_scraper/annual.py
tw_finreport_scraper/common.py
tw_finreport_scraper/main.py
tw_finreport_scraper/quarterly.py
tw_finreport_scraper/stocks.py
tw_finreport_scraper/symbol_lookup.json
tw_finreport_scraper-0.1.1.dist-info/METADATA
tw_finreport_scraper-0.1.1.dist-info/WHEEL
tw_finreport_scraper-0.1.1.dist-info/licenses/LICENSE
tw_finreport_scraper-0.1.1.dist-info/RECORD
