Metadata-Version: 2.4
Name: tw-finreport-scraper
Version: 0.1.1
Summary: A tool to scrape financial reports from TWSE
Author: abin
License: MIT
License-File: LICENSE
Requires-Python: >=3.8
Requires-Dist: beautifulsoup4>=4.12.0
Requires-Dist: playwright>=1.40.0
Requires-Dist: requests>=2.31.0
